pbsacct/__init__.py
pbsacct-3.4.6.dist-info/METADATA
pbsacct-3.4.6.dist-info/WHEEL
pbsacct-3.4.6.dist-info/top_level.txt
pbsacct-3.4.6.dist-info/RECORD
