Metadata-Version: 2.1
Name: pbsacct
Version: 3.4.6
Summary: Python library for parsing PBS accounting logs
Home-page: https://github.com/tabaer/pbstools
Author: Troy Baer
Author-email: tabaer@gmail.com
License: GPL v2
Platform: UNKNOWN
Classifier: Development Status :: 4 - Beta
Classifier: Intended Audience :: System Administrators
Classifier: License :: OSI Approved :: GNU General Public License v2 (GPLv2)
Classifier: Operating System :: POSIX
Classifier: Topic :: Scientific/Engineering :: Information Analysis
Classifier: Topic :: Software Development :: Libraries :: Python Modules
